[   {"id": 1, "top_id": 1, "tag_id": 1, "is_active": "true" },
    {"id": 2, "top_id": 1, "tag_id": 2, "is_active": "true" },    
    {"id": 3, "top_id": 2, "tag_id": 1, "is_active": "true" },    
    {"id": 4, "top_id": 3, "tag_id": 2, "is_active": "true" },    
    {"id": 5, "top_id": 4, "tag_id": 1, "is_active": "true" },    
    {"id": 6, "top_id": 4, "tag_id": 2, "is_active": "true" },    
    {"id": 7, "top_id": 5, "tag_id": 2, "is_active": "true" },    
    {"id": 8, "top_id": 6, "tag_id": 1, "is_active": "true" },    
    {"id": 9, "top_id": 7, "tag_id": 1, "is_active": "true" },    
    {"id": 10, "top_id": 7, "tag_id": 2, "is_active": "true" },    
    {"id": 11, "top_id": 8, "tag_id": 1, "is_active": "true" },    
    {"id": 12, "top_id": 8, "tag_id": 2, "is_active": "true" },    
    {"id": 13, "top_id": 9, "tag_id": 2, "is_active": "true" },    
    {"id": 14, "top_id": 10, "tag_id": 1, "is_active": "true" },    
    {"id": 15, "top_id": 11, "tag_id": 2, "is_active": "true" },    
    {"id": 16, "top_id": 12, "tag_id": 2, "is_active": "true" },    
    {"id": 17, "top_id": 13, "tag_id": 1, "is_active": "true" },    
    {"id": 18, "top_id": 13, "tag_id": 2, "is_active": "true" },    
    {"id": 19, "top_id": 14, "tag_id": 1, "is_active": "true" },    
    {"id": 20, "top_id": 14, "tag_id": 2, "is_active": "true" },    
    {"id": 21, "top_id": 15, "tag_id": 2, "is_active": "true" },    
    {"id": 22, "top_id": 16, "tag_id": 1, "is_active": "true" },    
    {"id": 23, "top_id": 17, "tag_id": 2, "is_active": "true" },    
    {"id": 24, "top_id": 18, "tag_id": 1, "is_active": "true" },    
    {"id": 25, "top_id": 18, "tag_id": 2, "is_active": "true" }
    ]

